setup.cfg
setup.py
fmtstr/__init__.py
fmtstr/bpythonparse.py
fmtstr/escseqparse.py
fmtstr/events.py
fmtstr/fmtfuncs.py
fmtstr/fmtstr.py
fmtstr/fsarray.py
fmtstr/termformatconstants.py
fmtstr/terminal.py
fmtstr/terminalcontrol.py
fmtstr.egg-info/PKG-INFO
fmtstr.egg-info/SOURCES.txt
fmtstr.egg-info/dependency_links.txt
fmtstr.egg-info/not-zip-safe
fmtstr.egg-info/top_level.txt