Metadata-Version: 1.1
Name: fmtstr
Version: 0.0.22
Summary: string-like objects marked up with terminal formatting
Home-page: https://github.com/thomasballinger/fmtstr
Author: Thomas Ballinger
Author-email: thomasballinger@gmail.com
License: MIT
Platform: UNKNOWN
Classifier: Development Status :: 3 - Alpha
Classifier: Environment :: Console
Classifier: Intended Audience :: Developers
Classifier: License :: OSI Approved :: MIT License
Classifier: Operating System :: POSIX
Classifier: Programming Language :: Python
